{
    "condition": {
        "name": "slot2",
        "url": "https://pokedex.mimo.dev/api/encounter-condition/4/"
    },
    "id": 9,
    "name": "slot2-ruby",
    "names": [
        {
            "language": {
                "name": "de",
                "url": "https://pokedex.mimo.dev/api/language/6/"
            },
            "name": "Rubin in Slot 2"
        },
        {
            "language": {
                "name": "en",
                "url": "https://pokedex.mimo.dev/api/language/9/"
            },
            "name": "Ruby in slot 2"
        },
        {
            "language": {
                "name": "fr",
                "url": "https://pokedex.mimo.dev/api/language/5/"
            },
            "name": "Rubis dans le slot 2"
        }
    ]
}