{
    "id": 122,
    "name": "Fart",
    "status": "Dead",
    "species": "Alien",
    "type": "Interdimensional gaseous being",
    "gender": "Male",
    "origin": {
        "name": "unknown",
        "url": ""
    },
    "location": {
        "name": "unknown",
        "url": ""
    },
    "image": "https://raw.githubusercontent.com/getmimo/things-api/main/files/rickandmorty/character/avatar/122.jpeg",
    "episode": [
        "https://rickandmorty.mimo.dev/api/episode/13"
    ],
    "url": "https://rickandmorty.mimo.dev/api/character/122",
    "created": "2017-12-26T17:19:40.474Z"
}