{
    "id": 266,
    "name": "Piece of Toast",
    "status": "Alive",
    "species": "unknown",
    "type": "Bread",
    "gender": "Genderless",
    "origin": {
        "name": "unknown",
        "url": ""
    },
    "location": {
        "name": "Interdimensional Cable",
        "url": "https://rickandmorty.mimo.dev/api/location/6"
    },
    "image": "https://raw.githubusercontent.com/getmimo/things-api/main/files/rickandmorty/character/avatar/266.jpeg",
    "episode": [
        "https://rickandmorty.mimo.dev/api/episode/8",
        "https://rickandmorty.mimo.dev/api/episode/17"
    ],
    "url": "https://rickandmorty.mimo.dev/api/character/266",
    "created": "2017-12-31T13:48:58.850Z"
}