{
    "id": 301,
    "name": "Ron Benson",
    "status": "Alive",
    "species": "Alien",
    "type": "Ring-nippled alien",
    "gender": "Male",
    "origin": {
        "name": "Unity's Planet",
        "url": "https://rickandmorty.mimo.dev/api/location/28"
    },
    "location": {
        "name": "Unity's Planet",
        "url": "https://rickandmorty.mimo.dev/api/location/28"
    },
    "image": "https://raw.githubusercontent.com/getmimo/things-api/main/files/rickandmorty/character/avatar/301.jpeg",
    "episode": [
        "https://rickandmorty.mimo.dev/api/episode/14"
    ],
    "url": "https://rickandmorty.mimo.dev/api/character/301",
    "created": "2018-01-05T14:02:20.902Z"
}