{
    "id": 431,
    "name": "Chair-homeless",
    "status": "Alive",
    "species": "Humanoid",
    "type": "Chair",
    "gender": "Male",
    "origin": {
        "name": "Earth (Chair Dimension)",
        "url": "https://rickandmorty.mimo.dev/api/location/74"
    },
    "location": {
        "name": "Earth (Chair Dimension)",
        "url": "https://rickandmorty.mimo.dev/api/location/74"
    },
    "image": "https://raw.githubusercontent.com/getmimo/things-api/main/files/rickandmorty/character/avatar/431.jpeg",
    "episode": [
        "https://rickandmorty.mimo.dev/api/episode/10"
    ],
    "url": "https://rickandmorty.mimo.dev/api/character/431",
    "created": "2018-04-16T22:01:17.927Z"
}