{
    "id": 524,
    "name": "Kirkland Brand Mr. Meeseeks",
    "status": "unknown",
    "species": "Humanoid",
    "type": "Meeseeks",
    "gender": "Male",
    "origin": {
        "name": "Mr. Meeseeks Box",
        "url": "https://rickandmorty.mimo.dev/api/location/53"
    },
    "location": {
        "name": "Earth (Replacement Dimension)",
        "url": "https://rickandmorty.mimo.dev/api/location/20"
    },
    "image": "https://raw.githubusercontent.com/getmimo/things-api/main/files/rickandmorty/character/avatar/524.jpeg",
    "episode": [
        "https://rickandmorty.mimo.dev/api/episode/32"
    ],
    "url": "https://rickandmorty.mimo.dev/api/character/524",
    "created": "2020-05-02T12:52:58.134Z"
}