{
    "id": 804,
    "name": "Andy",
    "status": "unknown",
    "species": "Human",
    "type": "Mascot",
    "gender": "Male",
    "origin": {
        "name": "unknown",
        "url": ""
    },
    "location": {
        "name": "Citadel of Ricks",
        "url": "https://rickandmorty.mimo.dev/api/location/3"
    },
    "image": "https://raw.githubusercontent.com/getmimo/things-api/main/files/rickandmorty/character/avatar/804.jpeg",
    "episode": [
        "https://rickandmorty.mimo.dev/api/episode/51"
    ],
    "url": "https://rickandmorty.mimo.dev/api/character/804",
    "created": "2021-11-02T13:19:19.807Z"
}