{
    "areas": [],
    "game_indices": [
        {
            "game_index": 326,
            "generation": {
                "name": "generation-vi",
                "url": "https://pokedex.mimo.dev/api/generation/6/"
            }
        }
    ],
    "id": 697,
    "name": "mirage-forest",
    "names": [
        {
            "language": {
                "name": "ja-Hrkt",
                "url": "https://pokedex.mimo.dev/api/language/1/"
            },
            "name": "\u30de\u30dc\u30ed\u30b7\u3082\u308a"
        },
        {
            "language": {
                "name": "ko",
                "url": "https://pokedex.mimo.dev/api/language/3/"
            },
            "name": "\ud658\uc0c1\uc232"
        },
        {
            "language": {
                "name": "fr",
                "url": "https://pokedex.mimo.dev/api/language/5/"
            },
            "name": "For\u00eat Mirage"
        },
        {
            "language": {
                "name": "de",
                "url": "https://pokedex.mimo.dev/api/language/6/"
            },
            "name": "Wunderwald"
        },
        {
            "language": {
                "name": "es",
                "url": "https://pokedex.mimo.dev/api/language/7/"
            },
            "name": "Bosque Espejismo"
        },
        {
            "language": {
                "name": "it",
                "url": "https://pokedex.mimo.dev/api/language/8/"
            },
            "name": "Selva Miraggio"
        },
        {
            "language": {
                "name": "en",
                "url": "https://pokedex.mimo.dev/api/language/9/"
            },
            "name": "Mirage Forest"
        },
        {
            "language": {
                "name": "ja",
                "url": "https://pokedex.mimo.dev/api/language/11/"
            },
            "name": "\u30de\u30dc\u30ed\u30b7\u68ee"
        }
    ],
    "region": {
        "name": "hoenn",
        "url": "https://pokedex.mimo.dev/api/region/3/"
    }
}