{
    "id": 8,
    "name": "Rixty Minutes",
    "air_date": "March 17, 2014",
    "episode": "S01E08",
    "characters": [
        "https://rickandmorty.mimo.dev/api/character/1",
        "https://rickandmorty.mimo.dev/api/character/2",
        "https://rickandmorty.mimo.dev/api/character/3",
        "https://rickandmorty.mimo.dev/api/character/4",
        "https://rickandmorty.mimo.dev/api/character/5",
        "https://rickandmorty.mimo.dev/api/character/20",
        "https://rickandmorty.mimo.dev/api/character/28",
        "https://rickandmorty.mimo.dev/api/character/29",
        "https://rickandmorty.mimo.dev/api/character/34",
        "https://rickandmorty.mimo.dev/api/character/37",
        "https://rickandmorty.mimo.dev/api/character/54",
        "https://rickandmorty.mimo.dev/api/character/88",
        "https://rickandmorty.mimo.dev/api/character/91",
        "https://rickandmorty.mimo.dev/api/character/129",
        "https://rickandmorty.mimo.dev/api/character/134",
        "https://rickandmorty.mimo.dev/api/character/136",
        "https://rickandmorty.mimo.dev/api/character/145",
        "https://rickandmorty.mimo.dev/api/character/153",
        "https://rickandmorty.mimo.dev/api/character/157",
        "https://rickandmorty.mimo.dev/api/character/176",
        "https://rickandmorty.mimo.dev/api/character/183",
        "https://rickandmorty.mimo.dev/api/character/184",
        "https://rickandmorty.mimo.dev/api/character/195",
        "https://rickandmorty.mimo.dev/api/character/207",
        "https://rickandmorty.mimo.dev/api/character/214",
        "https://rickandmorty.mimo.dev/api/character/222",
        "https://rickandmorty.mimo.dev/api/character/250",
        "https://rickandmorty.mimo.dev/api/character/266",
        "https://rickandmorty.mimo.dev/api/character/277",
        "https://rickandmorty.mimo.dev/api/character/279",
        "https://rickandmorty.mimo.dev/api/character/314",
        "https://rickandmorty.mimo.dev/api/character/315",
        "https://rickandmorty.mimo.dev/api/character/316",
        "https://rickandmorty.mimo.dev/api/character/317",
        "https://rickandmorty.mimo.dev/api/character/318",
        "https://rickandmorty.mimo.dev/api/character/351",
        "https://rickandmorty.mimo.dev/api/character/358",
        "https://rickandmorty.mimo.dev/api/character/367",
        "https://rickandmorty.mimo.dev/api/character/370",
        "https://rickandmorty.mimo.dev/api/character/373",
        "https://rickandmorty.mimo.dev/api/character/402",
        "https://rickandmorty.mimo.dev/api/character/403",
        "https://rickandmorty.mimo.dev/api/character/404",
        "https://rickandmorty.mimo.dev/api/character/405",
        "https://rickandmorty.mimo.dev/api/character/406",
        "https://rickandmorty.mimo.dev/api/character/407",
        "https://rickandmorty.mimo.dev/api/character/408",
        "https://rickandmorty.mimo.dev/api/character/409",
        "https://rickandmorty.mimo.dev/api/character/410",
        "https://rickandmorty.mimo.dev/api/character/411",
        "https://rickandmorty.mimo.dev/api/character/412",
        "https://rickandmorty.mimo.dev/api/character/413",
        "https://rickandmorty.mimo.dev/api/character/414",
        "https://rickandmorty.mimo.dev/api/character/415",
        "https://rickandmorty.mimo.dev/api/character/416",
        "https://rickandmorty.mimo.dev/api/character/417",
        "https://rickandmorty.mimo.dev/api/character/418"
    ],
    "url": "https://rickandmorty.mimo.dev/api/episode/8",
    "created": "2017-11-10T12:56:34.543Z"
}